jupyterlab_play_cell_button/__init__.py
jupyterlab_play_cell_button/_version.py
jupyterlab_play_cell_button/labextension/build_log.json
jupyterlab_play_cell_button/labextension/package.json
jupyterlab_play_cell_button/labextension/static/lib_index_js.aedef83afa12907abe94.js
jupyterlab_play_cell_button/labextension/static/lib_index_js.aedef83afa12907abe94.js.map
jupyterlab_play_cell_button/labextension/static/remoteEntry.b3099de2b3179eceeef5.js
jupyterlab_play_cell_button/labextension/static/remoteEntry.b3099de2b3179eceeef5.js.map
jupyterlab_play_cell_button/labextension/static/style.js
jupyterlab_play_cell_button/labextension/static/style_index_js.d6a2a7939fc0e21e1358.js
jupyterlab_play_cell_button/labextension/static/style_index_js.d6a2a7939fc0e21e1358.js.map
jupyterlab_play_cell_button/labextension/static/vendors-node_modules_css-loader_dist_runtime_api_js-node_modules_css-loader_dist_runtime_cssW-926fd9.a11a313820474e5199a1.js
jupyterlab_play_cell_button/labextension/static/vendors-node_modules_css-loader_dist_runtime_api_js-node_modules_css-loader_dist_runtime_cssW-926fd9.a11a313820474e5199a1.js.map
jupyterlab_play_cell_button-1.0.0.data/data/share/jupyter/labextensions/@epi2melabs/jupyterlab-play-cell-button/build_log.json
jupyterlab_play_cell_button-1.0.0.data/data/share/jupyter/labextensions/@epi2melabs/jupyterlab-play-cell-button/install.json
jupyterlab_play_cell_button-1.0.0.data/data/share/jupyter/labextensions/@epi2melabs/jupyterlab-play-cell-button/package.json
jupyterlab_play_cell_button-1.0.0.data/data/share/jupyter/labextensions/@epi2melabs/jupyterlab-play-cell-button/static/lib_index_js.aedef83afa12907abe94.js
jupyterlab_play_cell_button-1.0.0.data/data/share/jupyter/labextensions/@epi2melabs/jupyterlab-play-cell-button/static/lib_index_js.aedef83afa12907abe94.js.map
jupyterlab_play_cell_button-1.0.0.data/data/share/jupyter/labextensions/@epi2melabs/jupyterlab-play-cell-button/static/remoteEntry.b3099de2b3179eceeef5.js
jupyterlab_play_cell_button-1.0.0.dist-info/LICENSE
jupyterlab_play_cell_button-1.0.0.dist-info/METADATA
jupyterlab_play_cell_button-1.0.0.dist-info/WHEEL
jupyterlab_play_cell_button-1.0.0.dist-info/top_level.txt
jupyterlab_play_cell_button-1.0.0.dist-info/RECORD
