Metadata-Version: 2.1
Name: jupyterlab-play-cell-button
Version: 1.0.0
Summary: Adds a play button to cells in jupyterlab
Home-page: https://github.com/epi2me-labs/jupyterlab-play-cell-button
Author: epi2melabs
License: BSD-3-Clause
Keywords: Jupyter,JupyterLab,JupyterLab3
Platform: Linux
Platform: Mac OS X
Platform: Windows
Classifier: License :: OSI Approved :: BSD License
Classifier: Programming Language :: Python
Classifier: Programming Language :: Python :: 3
Classifier: Programming Language :: Python :: 3.6
Classifier: Programming Language :: Python :: 3.7
Classifier: Programming Language :: Python :: 3.8
Classifier: Programming Language :: Python :: 3.9
Classifier: Framework :: Jupyter
Requires-Python: >=3.6
Requires-Dist: jupyter-server (<2,>=1.6)
